[
    {
        "id": 94099801,
        "name": "ドバイ観光 高さにこだわる女神様",
        "place": "",
        "chapter": "",
        "category": "",
        "qp": 1900,
        "drop": [
            {
                "id": 9407960,
                "name": "眺望絶佳、神韻縹渺",
                "type": "Craft Essence",
                "dropPriority": 9005
            },
            {
                "id": 6512,
                "name": "竜の牙",
                "type": "Item",
                "dropPriority": 8200
            },
            {
                "id": 6004,
                "name": "騎の輝石",
                "type": "Item",
                "dropPriority": 6097
            },
            {
                "id": 7004,
                "name": "ライダーピース",
                "type": "Item",
                "dropPriority": 5197
            },
            {
                "id": 94099505,
                "name": "ドバイ観光ポイント",
                "type": "Point",
                "dropPriority": 3005
            },
            {
                "id": 94099502,
                "name": "ラグジュアリーキャメル",
                "type": "Item",
                "dropPriority": 2002
            },
            {
                "id": 94099501,
                "name": "リッチデーツ",
                "type": "Item",
                "dropPriority": 2001
            }
        ],
        "dropItemNum": -1,
        "shortname": "ドバイ観光 高さにこだわる女神様"
    },
    {
        "id": 94099802,
        "name": "ドバイ観光 不毀のバリケード",
        "place": "",
        "chapter": "",
        "category": "",
        "qp": 2900,
        "drop": [
            {
                "id": 9407970,
                "name": "黄昏の風に吹かれて",
                "type": "Craft Essence",
                "dropPriority": 9005
            },
            {
                "id": 6534,
                "name": "励振火薬",
                "type": "Item",
                "dropPriority": 8105
            },
            {
                "id": 6103,
                "name": "槍の魔石",
                "type": "Item",
                "dropPriority": 6198
            },
            {
                "id": 6003,
                "name": "槍の輝石",
                "type": "Item",
                "dropPriority": 6098
            },
            {
                "id": 7003,
                "name": "ランサーピース",
                "type": "Item",
                "dropPriority": 5198
            },
            {
                "id": 94099505,
                "name": "ドバイ観光ポイント",
                "type": "Point",
                "dropPriority": 3005
            },
            {
                "id": 94099503,
                "name": "ゴールデンポット",
                "type": "Item",
                "dropPriority": 2003
            },
            {
                "id": 94099502,
                "name": "ラグジュアリーキャメル",
                "type": "Item",
                "dropPriority": 2002
            }
        ],
        "dropItemNum": -1,
        "shortname": "ドバイ観光 不毀のバリケード"
    },
    {
        "id": 94099803,
        "name": "ドバイ観光 ハヌマーンも認めた味",
        "place": "",
        "chapter": "",
        "category": "",
        "qp": 4400,
        "drop": [
            {
                "id": 9407960,
                "name": "眺望絶佳、神韻縹渺",
                "type": "Craft Essence",
                "dropPriority": 9005
            },
            {
                "id": 6552,
                "name": "忘れじの灰",
                "type": "Item",
                "dropPriority": 8108
            },
            {
                "id": 6101,
                "name": "剣の魔石",
                "type": "Item",
                "dropPriority": 6200
            },
            {
                "id": 6001,
                "name": "剣の輝石",
                "type": "Item",
                "dropPriority": 6100
            },
            {
                "id": 7001,
                "name": "セイバーピース",
                "type": "Item",
                "dropPriority": 5200
            },
            {
                "id": 94099505,
                "name": "ドバイ観光ポイント",
                "type": "Point",
                "dropPriority": 3005
            },
            {
                "id": 94099503,
                "name": "ゴールデンポット",
                "type": "Item",
                "dropPriority": 2003
            },
            {
                "id": 94099501,
                "name": "リッチデーツ",
                "type": "Item",
                "dropPriority": 2001
            }
        ],
        "dropItemNum": -1,
        "shortname": "ドバイ観光 ハヌマーンも認めた味"
    },
    {
        "id": 94099804,
        "name": "ドバイ観光 ３カウントが聞こえる",
        "place": "",
        "chapter": "",
        "category": "",
        "qp": 5400,
        "drop": [
            {
                "id": 9407970,
                "name": "黄昏の風に吹かれて",
                "type": "Craft Essence",
                "dropPriority": 9005
            },
            {
                "id": 6546,
                "name": "悠久の実",
                "type": "Item",
                "dropPriority": 8407
            },
            {
                "id": 6535,
                "name": "永遠結氷",
                "type": "Item",
                "dropPriority": 8311
            },
            {
                "id": 6107,
                "name": "狂の魔石",
                "type": "Item",
                "dropPriority": 6194
            },
            {
                "id": 6007,
                "name": "狂の輝石",
                "type": "Item",
                "dropPriority": 6094
            },
            {
                "id": 7004,
                "name": "ライダーピース",
                "type": "Item",
                "dropPriority": 5197
            },
            {
                "id": 7005,
                "name": "キャスターピース",
                "type": "Item",
                "dropPriority": 5196
            },
            {
                "id": 7006,
                "name": "アサシンピース",
                "type": "Item",
                "dropPriority": 5195
            },
            {
                "id": 7007,
                "name": "バーサーカーピース",
                "type": "Item",
                "dropPriority": 5194
            },
            {
                "id": 94099505,
                "name": "ドバイ観光ポイント",
                "type": "Point",
                "dropPriority": 3005
            },
            {
                "id": 94099502,
                "name": "ラグジュアリーキャメル",
                "type": "Item",
                "dropPriority": 2002
            },
            {
                "id": 94099501,
                "name": "リッチデーツ",
                "type": "Item",
                "dropPriority": 2001
            }
        ],
        "dropItemNum": -1,
        "shortname": "ドバイ観光 ３カウントが聞こえる"
    },
    {
        "id": 94099805,
        "name": "ドバイ観光 百面相の洋品店",
        "place": "",
        "chapter": "",
        "category": "",
        "qp": 6400,
        "drop": [
            {
                "id": 9407960,
                "name": "眺望絶佳、神韻縹渺",
                "type": "Craft Essence",
                "dropPriority": 9005
            },
            {
                "id": 6528,
                "name": "原初の産毛",
                "type": "Item",
                "dropPriority": 8405
            },
            {
                "id": 6508,
                "name": "ゴーストランタン",
                "type": "Item",
                "dropPriority": 8300
            },
            {
                "id": 6106,
                "name": "殺の魔石",
                "type": "Item",
                "dropPriority": 6195
            },
            {
                "id": 6006,
                "name": "殺の輝石",
                "type": "Item",
                "dropPriority": 6095
            },
            {
                "id": 7106,
                "name": "アサシンモニュメント",
                "type": "Item",
                "dropPriority": 5295
            },
            {
                "id": 94099505,
                "name": "ドバイ観光ポイント",
                "type": "Point",
                "dropPriority": 3005
            },
            {
                "id": 94099503,
                "name": "ゴールデンポット",
                "type": "Item",
                "dropPriority": 2003
            },
            {
                "id": 94099502,
                "name": "ラグジュアリーキャメル",
                "type": "Item",
                "dropPriority": 2002
            }
        ],
        "dropItemNum": -1,
        "shortname": "ドバイ観光 百面相の洋品店"
    },
    {
        "id": 94099806,
        "name": "ドバイ観光 買うべきか買わざるべきか",
        "place": "",
        "chapter": "",
        "category": "",
        "qp": 7400,
        "drop": [
            {
                "id": 9407970,
                "name": "黄昏の風に吹かれて",
                "type": "Craft Essence",
                "dropPriority": 9005
            },
            {
                "id": 6509,
                "name": "蛇の宝玉",
                "type": "Item",
                "dropPriority": 8307
            },
            {
                "id": 6105,
                "name": "術の魔石",
                "type": "Item",
                "dropPriority": 6196
            },
            {
                "id": 6005,
                "name": "術の輝石",
                "type": "Item",
                "dropPriority": 6096
            },
            {
                "id": 7105,
                "name": "キャスターモニュメント",
                "type": "Item",
                "dropPriority": 5296
            },
            {
                "id": 94099505,
                "name": "ドバイ観光ポイント",
                "type": "Point",
                "dropPriority": 3005
            },
            {
                "id": 94099503,
                "name": "ゴールデンポット",
                "type": "Item",
                "dropPriority": 2003
            },
            {
                "id": 94099501,
                "name": "リッチデーツ",
                "type": "Item",
                "dropPriority": 2001
            }
        ],
        "dropItemNum": -1,
        "shortname": "ドバイ観光 買うべきか買わざるべきか"
    },
    {
        "id": 94099807,
        "name": "ドバイ観光 フードデリバリー戦争",
        "place": "",
        "chapter": "",
        "category": "",
        "qp": 7900,
        "drop": [
            {
                "id": 9407960,
                "name": "眺望絶佳、神韻縹渺",
                "type": "Craft Essence",
                "dropPriority": 9005
            },
            {
                "id": 6521,
                "name": "黒獣脂",
                "type": "Item",
                "dropPriority": 8403
            },
            {
                "id": 6526,
                "name": "追憶の貝殻",
                "type": "Item",
                "dropPriority": 8308
            },
            {
                "id": 6107,
                "name": "狂の魔石",
                "type": "Item",
                "dropPriority": 6194
            },
            {
                "id": 6007,
                "name": "狂の輝石",
                "type": "Item",
                "dropPriority": 6094
            },
            {
                "id": 7107,
                "name": "バーサーカーモニュメント",
                "type": "Item",
                "dropPriority": 5294
            },
            {
                "id": 94099505,
                "name": "ドバイ観光ポイント",
                "type": "Point",
                "dropPriority": 3005
            },
            {
                "id": 94099502,
                "name": "ラグジュアリーキャメル",
                "type": "Item",
                "dropPriority": 2002
            },
            {
                "id": 94099501,
                "name": "リッチデーツ",
                "type": "Item",
                "dropPriority": 2001
            }
        ],
        "dropItemNum": -1,
        "shortname": "ドバイ観光 フードデリバリー戦争"
    },
    {
        "id": 94099808,
        "name": "ドバイ観光 砂漠の愛の逃避行？",
        "place": "",
        "chapter": "",
        "category": "",
        "qp": 8400,
        "drop": [
            {
                "id": 9407970,
                "name": "黄昏の風に吹かれて",
                "type": "Craft Essence",
                "dropPriority": 9005
            },
            {
                "id": 6531,
                "name": "奇奇神酒",
                "type": "Item",
                "dropPriority": 8505
            },
            {
                "id": 6547,
                "name": "虹の糸玉",
                "type": "Item",
                "dropPriority": 8318
            },
            {
                "id": 6202,
                "name": "弓の秘石",
                "type": "Item",
                "dropPriority": 6299
            },
            {
                "id": 6102,
                "name": "弓の魔石",
                "type": "Item",
                "dropPriority": 6199
            },
            {
                "id": 7102,
                "name": "アーチャーモニュメント",
                "type": "Item",
                "dropPriority": 5299
            },
            {
                "id": 94099505,
                "name": "ドバイ観光ポイント",
                "type": "Point",
                "dropPriority": 3005
            },
            {
                "id": 94099503,
                "name": "ゴールデンポット",
                "type": "Item",
                "dropPriority": 2003
            },
            {
                "id": 94099502,
                "name": "ラグジュアリーキャメル",
                "type": "Item",
                "dropPriority": 2002
            }
        ],
        "dropItemNum": -1,
        "shortname": "ドバイ観光 砂漠の愛の逃避行？"
    },
    {
        "id": 94099809,
        "name": "ドバイ観光 ご利用は計画的に",
        "place": "",
        "chapter": "",
        "category": "",
        "qp": 8900,
        "drop": [
            {
                "id": 9407960,
                "name": "眺望絶佳、神韻縹渺",
                "type": "Craft Essence",
                "dropPriority": 9005
            },
            {
                "id": 6506,
                "name": "竜の逆鱗",
                "type": "Item",
                "dropPriority": 8501
            },
            {
                "id": 6524,
                "name": "大騎士勲章",
                "type": "Item",
                "dropPriority": 8309
            },
            {
                "id": 6206,
                "name": "殺の秘石",
                "type": "Item",
                "dropPriority": 6295
            },
            {
                "id": 6106,
                "name": "殺の魔石",
                "type": "Item",
                "dropPriority": 6195
            },
            {
                "id": 7106,
                "name": "アサシンモニュメント",
                "type": "Item",
                "dropPriority": 5295
            },
            {
                "id": 94099505,
                "name": "ドバイ観光ポイント",
                "type": "Point",
                "dropPriority": 3005
            },
            {
                "id": 94099503,
                "name": "ゴールデンポット",
                "type": "Item",
                "dropPriority": 2003
            },
            {
                "id": 94099501,
                "name": "リッチデーツ",
                "type": "Item",
                "dropPriority": 2001
            }
        ],
        "dropItemNum": -1,
        "shortname": "ドバイ観光 ご利用は計画的に"
    },
    {
        "id": 94099810,
        "name": "ドバイ観光 落下した先で、わしは",
        "place": "",
        "chapter": "",
        "category": "",
        "qp": 9400,
        "drop": [
            {
                "id": 9407970,
                "name": "黄昏の風に吹かれて",
                "type": "Craft Essence",
                "dropPriority": 9005
            },
            {
                "id": 6527,
                "name": "万死の毒針",
                "type": "Item",
                "dropPriority": 8202
            },
            {
                "id": 6516,
                "name": "凶骨",
                "type": "Item",
                "dropPriority": 8101
            },
            {
                "id": 6204,
                "name": "騎の秘石",
                "type": "Item",
                "dropPriority": 6297
            },
            {
                "id": 6004,
                "name": "騎の輝石",
                "type": "Item",
                "dropPriority": 6097
            },
            {
                "id": 7104,
                "name": "ライダーモニュメント",
                "type": "Item",
                "dropPriority": 5297
            },
            {
                "id": 7105,
                "name": "キャスターモニュメント",
                "type": "Item",
                "dropPriority": 5296
            },
            {
                "id": 7106,
                "name": "アサシンモニュメント",
                "type": "Item",
                "dropPriority": 5295
            },
            {
                "id": 7107,
                "name": "バーサーカーモニュメント",
                "type": "Item",
                "dropPriority": 5294
            },
            {
                "id": 94099505,
                "name": "ドバイ観光ポイント",
                "type": "Point",
                "dropPriority": 3005
            }
        ],
        "dropItemNum": -1,
        "shortname": "ドバイ観光 落下した先で、わしは"
    },
    {
        "id": 94099811,
        "name": "ドバイ観光 王の晩餐 ～準備中～",
        "place": "",
        "chapter": "",
        "category": "",
        "qp": 11280,
        "drop": [
            {
                "id": 9407960,
                "name": "眺望絶佳、神韻縹渺",
                "type": "Craft Essence",
                "dropPriority": 9005
            },
            {
                "id": 9407970,
                "name": "黄昏の風に吹かれて",
                "type": "Craft Essence",
                "dropPriority": 9005
            },
            {
                "id": 6544,
                "name": "煌星のカケラ",
                "type": "Item",
                "dropPriority": 8508
            },
            {
                "id": 6556,
                "name": "エーテル収光体",
                "type": "Item",
                "dropPriority": 8321
            },
            {
                "id": 6203,
                "name": "槍の秘石",
                "type": "Item",
                "dropPriority": 6298
            },
            {
                "id": 6103,
                "name": "槍の魔石",
                "type": "Item",
                "dropPriority": 6198
            },
            {
                "id": 6003,
                "name": "槍の輝石",
                "type": "Item",
                "dropPriority": 6098
            },
            {
                "id": 7104,
                "name": "ライダーモニュメント",
                "type": "Item",
                "dropPriority": 5297
            },
            {
                "id": 7105,
                "name": "キャスターモニュメント",
                "type": "Item",
                "dropPriority": 5296
            },
            {
                "id": 7106,
                "name": "アサシンモニュメント",
                "type": "Item",
                "dropPriority": 5295
            },
            {
                "id": 7107,
                "name": "バーサーカーモニュメント",
                "type": "Item",
                "dropPriority": 5294
            },
            {
                "id": 94099505,
                "name": "ドバイ観光ポイント",
                "type": "Point",
                "dropPriority": 3005
            },
            {
                "id": 94099503,
                "name": "ゴールデンポット",
                "type": "Item",
                "dropPriority": 2003
            },
            {
                "id": 94099502,
                "name": "ラグジュアリーキャメル",
                "type": "Item",
                "dropPriority": 2002
            },
            {
                "id": 94099501,
                "name": "リッチデーツ",
                "type": "Item",
                "dropPriority": 2001
            }
        ],
        "dropItemNum": -1,
        "shortname": "ドバイ観光 王の晩餐 ～準備中～"
    }
]