[
    {
        "id": 94088901,
        "name": "現地調査！ 聖杯の行方！",
        "place": "",
        "chapter": "",
        "qp": 1900,
        "drop": [
            {
                "id": 9407400,
                "name": "ほしの歩き方",
                "type": "Craft Essence",
                "dropPriority": 9005
            },
            {
                "id": 6503,
                "name": "英雄の証",
                "type": "Item",
                "dropPriority": 8100
            },
            {
                "id": 6003,
                "name": "槍の輝石",
                "type": "Item",
                "dropPriority": 6098
            },
            {
                "id": 7003,
                "name": "ランサーピース",
                "type": "Item",
                "dropPriority": 5198
            },
            {
                "id": 94088802,
                "name": "カンガルーブーメラン",
                "type": "Item",
                "dropPriority": 2002
            },
            {
                "id": 94088801,
                "name": "カモノハシクッキー",
                "type": "Item",
                "dropPriority": 2001
            }
        ],
        "dropItemNum": -1,
        "shortname": "現地調査！ 聖杯の行方！"
    },
    {
        "id": 94088902,
        "name": "現地調査！ 街中の騒動！",
        "place": "",
        "chapter": "",
        "qp": 2900,
        "drop": [
            {
                "id": 9407400,
                "name": "ほしの歩き方",
                "type": "Craft Essence",
                "dropPriority": 9005
            },
            {
                "id": 6534,
                "name": "励振火薬",
                "type": "Item",
                "dropPriority": 8105
            },
            {
                "id": 6002,
                "name": "弓の輝石",
                "type": "Item",
                "dropPriority": 6099
            },
            {
                "id": 7002,
                "name": "アーチャーピース",
                "type": "Item",
                "dropPriority": 5199
            },
            {
                "id": 94088803,
                "name": "ダッココアラ",
                "type": "Item",
                "dropPriority": 2003
            },
            {
                "id": 94088802,
                "name": "カンガルーブーメラン",
                "type": "Item",
                "dropPriority": 2002
            }
        ],
        "dropItemNum": -1,
        "shortname": "現地調査！ 街中の騒動！"
    },
    {
        "id": 94088903,
        "name": "現地調査！ 魔獣襲来！",
        "place": "",
        "chapter": "",
        "qp": 4400,
        "drop": [
            {
                "id": 9407400,
                "name": "ほしの歩き方",
                "type": "Craft Essence",
                "dropPriority": 9005
            },
            {
                "id": 6502,
                "name": "世界樹の種",
                "type": "Item",
                "dropPriority": 8203
            },
            {
                "id": 6101,
                "name": "剣の魔石",
                "type": "Item",
                "dropPriority": 6200
            },
            {
                "id": 6001,
                "name": "剣の輝石",
                "type": "Item",
                "dropPriority": 6100
            },
            {
                "id": 7001,
                "name": "セイバーピース",
                "type": "Item",
                "dropPriority": 5200
            },
            {
                "id": 94088803,
                "name": "ダッココアラ",
                "type": "Item",
                "dropPriority": 2003
            },
            {
                "id": 94088801,
                "name": "カモノハシクッキー",
                "type": "Item",
                "dropPriority": 2001
            }
        ],
        "dropItemNum": -1,
        "shortname": "現地調査！ 魔獣襲来！"
    },
    {
        "id": 94088904,
        "name": "現地調査！ 闇夜の訪れ！",
        "place": "",
        "chapter": "",
        "qp": 5400,
        "drop": [
            {
                "id": 9407400,
                "name": "ほしの歩き方",
                "type": "Craft Essence",
                "dropPriority": 9005
            },
            {
                "id": 6521,
                "name": "黒獣脂",
                "type": "Item",
                "dropPriority": 8403
            },
            {
                "id": 6522,
                "name": "愚者の鎖",
                "type": "Item",
                "dropPriority": 8102
            },
            {
                "id": 6107,
                "name": "狂の魔石",
                "type": "Item",
                "dropPriority": 6194
            },
            {
                "id": 6007,
                "name": "狂の輝石",
                "type": "Item",
                "dropPriority": 6094
            },
            {
                "id": 7007,
                "name": "バーサーカーピース",
                "type": "Item",
                "dropPriority": 5194
            },
            {
                "id": 94088802,
                "name": "カンガルーブーメラン",
                "type": "Item",
                "dropPriority": 2002
            },
            {
                "id": 94088801,
                "name": "カモノハシクッキー",
                "type": "Item",
                "dropPriority": 2001
            }
        ],
        "dropItemNum": -1,
        "shortname": "現地調査！ 闇夜の訪れ！"
    },
    {
        "id": 94088905,
        "name": "世界旅行！ 灼熱の常夏ビーチ！",
        "place": "",
        "chapter": "",
        "qp": 6400,
        "drop": [
            {
                "id": 9407400,
                "name": "ほしの歩き方",
                "type": "Craft Essence",
                "dropPriority": 9005
            },
            {
                "id": 6523,
                "name": "封魔のランプ",
                "type": "Item",
                "dropPriority": 8404
            },
            {
                "id": 6505,
                "name": "虚影の塵",
                "type": "Item",
                "dropPriority": 8201
            },
            {
                "id": 6105,
                "name": "術の魔石",
                "type": "Item",
                "dropPriority": 6196
            },
            {
                "id": 6005,
                "name": "術の輝石",
                "type": "Item",
                "dropPriority": 6096
            },
            {
                "id": 7105,
                "name": "キャスターモニュメント",
                "type": "Item",
                "dropPriority": 5296
            },
            {
                "id": 94088803,
                "name": "ダッココアラ",
                "type": "Item",
                "dropPriority": 2003
            },
            {
                "id": 94088802,
                "name": "カンガルーブーメラン",
                "type": "Item",
                "dropPriority": 2002
            }
        ],
        "dropItemNum": -1,
        "shortname": "世界旅行！ 灼熱の常夏ビーチ！"
    },
    {
        "id": 94088906,
        "name": "世界旅行！ キャンプ地の怨霊！",
        "place": "",
        "chapter": "",
        "qp": 7400,
        "drop": [
            {
                "id": 9407400,
                "name": "ほしの歩き方",
                "type": "Craft Essence",
                "dropPriority": 9005
            },
            {
                "id": 6508,
                "name": "ゴーストランタン",
                "type": "Item",
                "dropPriority": 8300
            },
            {
                "id": 6533,
                "name": "宵哭きの鉄杭",
                "type": "Item",
                "dropPriority": 8104
            },
            {
                "id": 6104,
                "name": "騎の魔石",
                "type": "Item",
                "dropPriority": 6197
            },
            {
                "id": 6004,
                "name": "騎の輝石",
                "type": "Item",
                "dropPriority": 6097
            },
            {
                "id": 7104,
                "name": "ライダーモニュメント",
                "type": "Item",
                "dropPriority": 5297
            },
            {
                "id": 94088803,
                "name": "ダッココアラ",
                "type": "Item",
                "dropPriority": 2003
            },
            {
                "id": 94088801,
                "name": "カモノハシクッキー",
                "type": "Item",
                "dropPriority": 2001
            }
        ],
        "dropItemNum": -1,
        "shortname": "世界旅行！ キャンプ地の怨霊！"
    },
    {
        "id": 94088907,
        "name": "世界旅行！ 砂塵舞う砂漠にて！",
        "place": "",
        "chapter": "",
        "qp": 7900,
        "drop": [
            {
                "id": 9407400,
                "name": "ほしの歩き方",
                "type": "Craft Essence",
                "dropPriority": 9005
            },
            {
                "id": 6501,
                "name": "鳳凰の羽根",
                "type": "Item",
                "dropPriority": 8306
            },
            {
                "id": 6510,
                "name": "無間の歯車",
                "type": "Item",
                "dropPriority": 8302
            },
            {
                "id": 6102,
                "name": "弓の魔石",
                "type": "Item",
                "dropPriority": 6199
            },
            {
                "id": 6002,
                "name": "弓の輝石",
                "type": "Item",
                "dropPriority": 6099
            },
            {
                "id": 7102,
                "name": "アーチャーモニュメント",
                "type": "Item",
                "dropPriority": 5299
            },
            {
                "id": 94088802,
                "name": "カンガルーブーメラン",
                "type": "Item",
                "dropPriority": 2002
            },
            {
                "id": 94088801,
                "name": "カモノハシクッキー",
                "type": "Item",
                "dropPriority": 2001
            }
        ],
        "dropItemNum": -1,
        "shortname": "世界旅行！ 砂塵舞う砂漠にて！"
    },
    {
        "id": 94088908,
        "name": "世界旅行！ ハロウィンの騒動！",
        "place": "",
        "chapter": "",
        "qp": 8400,
        "drop": [
            {
                "id": 9407400,
                "name": "ほしの歩き方",
                "type": "Craft Essence",
                "dropPriority": 9005
            },
            {
                "id": 6532,
                "name": "枯淡勾玉",
                "type": "Item",
                "dropPriority": 8310
            },
            {
                "id": 6515,
                "name": "八連双晶",
                "type": "Item",
                "dropPriority": 8301
            },
            {
                "id": 6101,
                "name": "剣の魔石",
                "type": "Item",
                "dropPriority": 6200
            },
            {
                "id": 6001,
                "name": "剣の輝石",
                "type": "Item",
                "dropPriority": 6100
            },
            {
                "id": 7101,
                "name": "セイバーモニュメント",
                "type": "Item",
                "dropPriority": 5300
            },
            {
                "id": 94088803,
                "name": "ダッココアラ",
                "type": "Item",
                "dropPriority": 2003
            },
            {
                "id": 94088802,
                "name": "カンガルーブーメラン",
                "type": "Item",
                "dropPriority": 2002
            }
        ],
        "dropItemNum": -1,
        "shortname": "世界旅行！ ハロウィンの騒動！"
    }
]