[
    {
        "id": 94067101,
        "name": "廃ビル探索 初級",
        "place": "",
        "chapter": "",
        "qp": 1900,
        "drop": [
            {
                "id": 6508,
                "name": "ゴーストランタン",
                "type": "Item",
                "dropPriority": 8300
            },
            {
                "id": 6006,
                "name": "殺の輝石",
                "type": "Item",
                "dropPriority": 6095
            },
            {
                "id": 94067002,
                "name": "クールバインダー",
                "type": "Item",
                "dropPriority": 2002
            },
            {
                "id": 94067001,
                "name": "インテリペーパー",
                "type": "Item",
                "dropPriority": 2001
            }
        ],
        "dropItemNum": -1,
        "shortname": "廃ビル探索 初級"
    },
    {
        "id": 94067102,
        "name": "廃ビル探索 中級",
        "place": "",
        "chapter": "",
        "qp": 2900,
        "drop": [
            {
                "id": 6516,
                "name": "凶骨",
                "type": "Item",
                "dropPriority": 8101
            },
            {
                "id": 6007,
                "name": "狂の輝石",
                "type": "Item",
                "dropPriority": 6094
            },
            {
                "id": 94067003,
                "name": "スマートペン",
                "type": "Item",
                "dropPriority": 2003
            },
            {
                "id": 94067002,
                "name": "クールバインダー",
                "type": "Item",
                "dropPriority": 2002
            }
        ],
        "dropItemNum": -1,
        "shortname": "廃ビル探索 中級"
    },
    {
        "id": 94067103,
        "name": "廃ビル探索 上級",
        "place": "",
        "chapter": "",
        "qp": 4400,
        "drop": [
            {
                "id": 6534,
                "name": "励振火薬",
                "type": "Item",
                "dropPriority": 8105
            },
            {
                "id": 6102,
                "name": "弓の魔石",
                "type": "Item",
                "dropPriority": 6199
            },
            {
                "id": 6002,
                "name": "弓の輝石",
                "type": "Item",
                "dropPriority": 6099
            },
            {
                "id": 94067003,
                "name": "スマートペン",
                "type": "Item",
                "dropPriority": 2003
            },
            {
                "id": 94067001,
                "name": "インテリペーパー",
                "type": "Item",
                "dropPriority": 2001
            }
        ],
        "dropItemNum": -1,
        "shortname": "廃ビル探索 上級"
    }
]